setup.cfg
setup.py
pycaseta/__init__.py
pycaseta/api.py
pycaseta.egg-info/PKG-INFO
pycaseta.egg-info/SOURCES.txt
pycaseta.egg-info/dependency_links.txt
pycaseta.egg-info/requires.txt
pycaseta.egg-info/top_level.txt
pycaseta.egg-info/zip-safe
pycaseta/devices/__init__.py
pycaseta/devices/dummy/__init__.py
pycaseta/devices/dummy/bridge.py
pycaseta/devices/standard/__init__.py
pycaseta/devices/standard/base.py