Metadata-Version: 1.0
Name: pycaseta
Version: 0.1.0
Summary: Access Caseta devices via the Integration API (telnet)
Home-page: http://githhub.com/kecorbin/python-caseta
Author: Kevin Corbin
Author-email: UNKNOWN
License: MIT
Platform: UNKNOWN
